[
  {
    "version": "1",
    "extend": "",
    "validTransactions": [
      {
        "type": "1",
        "name": "io.nuls.test.TestTransaction",
        "handler": "io.nuls.test.TestTransactionHandler",
        "validate": "validate",
        "commit": "commit",
        "rollback": "rollback"
      }
    ],
    "validMessages": [
      {
        "name": "io.nuls.block.message.BlockMessage",
        "handlers": [
          {
            "name": "io.nuls.block.rpc.BlockHandler#process"
          }
        ]
      },
      {
        "name": "io.nuls.block.message.CompleteMessage",
        "handlers": [
          {
            "name": "io.nuls.block.rpc.CompleteHandler#process"
          }
        ]
      },
      {
        "name": "io.nuls.block.message.HashListMessage",
        "handlers": [
          {
            "name": "io.nuls.block.rpc.GetTxGroupHandler#process"
          }
        ]
      },
      {
        "name": "io.nuls.block.message.HashMessage",
        "handlers": [
          {
            "name": "io.nuls.block.rpc.ForwardSmallBlockHandler#process"
          },
          {
            "name": "io.nuls.block.rpc.GetBlockHandler#process"
          },
          {
            "name": "io.nuls.block.rpc.GetSmallBlockHandler#process"
          }
        ]
      },
      {
        "name": "io.nuls.block.message.HeightRangeMessage",
        "handlers": [
          {
            "name": "io.nuls.block.rpc.GetBlocksHandler#process"
          }
        ]
      },
      {
        "name": "io.nuls.block.message.SmallBlockMessage",
        "handlers": [
          {
            "name": "io.nuls.block.rpc.SmallBlockHandler#process"
          }
        ]
      },
      {
        "name": "io.nuls.block.message.TxGroupMessage",
        "handlers": [
          {
            "name": "io.nuls.block.rpc.TxGroupHandler#process"
          }
        ]
      },
      {
        "name": "io.nuls.block.test.TestMessage",
        "handlers": [
          {
            "name": "io.nuls.block.test.TestMessageHandler#process"
          }
        ]
      }
    ],
    "invalidTransactions": [],
    "invalidMessages": []
  },
  {
    "version": "2",
    "extend": "1",
    "validTransactions": [],
    "validMessages": [
      {
        "name": "io.nuls.block.message.BlockMessage",
        "handlers": [
          {
            "name": "io.nuls.block.rpc.BlockHandler#process2"
          }
        ]
      }
    ],
    "invalidTransactions": [
      {
        "name": "io.nuls.test.TestTransaction"
      }
    ],
    "invalidMessages": [
      {
        "name": "io.nuls.block.test.TestMessage"
      }
    ]
  }
]